{"036 N RACINE AVE, Lakeview, Chicago, Illinois": ["41.88251", "-87.65684"], "035 N RACINE AVE, Lakeview, Chicago, Illinois": ["41.88251", "-87.65684"], "012 W BARRY AVE, Lakeview, Chicago, Illinois": ["41.93773", "-87.63903"], "029 N Sheridan Rd, Lakeview, Chicago, Illinois": ["41.99868", "-87.65725"], "028 N Seminary Ave, Lakeview, Chicago, Illinois": ["41.91659", "-87.65537"], "015 W Belle Plaine Ave, Lakeview, Chicago, Illinois": ["41.95548", "-87.74669"], "0000 W H5 ST, O'Hare, Chicago, Illinois": ["41.81259", "-87.60872"], "030 N Southport Ave, Lakeview, Chicago, Illinois": ["41.91861", "-87.66309"], "036 N Southport Ave, Lakeview, Chicago, Illinois": ["41.94375", "-87.66344"], "0000 W K10 10B ST, O'Hare, Chicago, Illinois": ["41.81259", "-87.60872"], "037 N RACINE AVE, Lakeview, Chicago, Illinois": ["41.88251", "-87.65684"], "017 S WENTWORTH ST, Near South Side, Chicago, Illinois": ["41.87951", "-87.77069"], "006 W SURF ST, Lakeview, Chicago, Illinois": ["41.93435", "-87.63908"], "038 N KENMORE AVE, Lakeview, Chicago, Illinois": ["41.97138", "-87.65589"], "014 W BARRY AVE, Lakeview, Chicago, Illinois": ["41.93773", "-87.63903"], "049 S DAN RYAN XPRS OB, Fuller Park, Chicago, Illinois": ["41.84820", "-87.62898"], "036 N CLARK ST, Lakeview, Chicago, Illinois": ["41.88321", "-87.63062"], "033 N Marshfield Ave, Lakeview, Chicago, Illinois": ["41.88905", "-87.66802"], "012 W MELROSE ST, Lakeview, Chicago, Illinois": ["41.94137", "-87.64047"], "055 S COTTAGE GROVE AVE, Washington Park, Chicago, Illinois": ["41.84772", "-87.68642"], "017 W Barry Ave, Lakeview, Chicago, Illinois": ["41.93773", "-87.63903"], "028 N Racine Ave, Lakeview, Chicago, Illinois": ["41.88251", "-87.65684"], "035 N Clark St, Lakeview, Chicago, Illinois": ["41.88321", "-87.63062"], "015 W OAKDALE AVE, Lakeview, Chicago, Illinois": ["41.93560", "-87.63831"], "008 W DAKIN ST, Lakeview, Chicago, Illinois": ["41.95364", "-87.65068"], "040 N SOUTHPORT AVE, Lakeview, Chicago, Illinois": ["41.91861", "-87.66309"], "006 W Grace ST, Lakeview, Chicago, Illinois": ["41.95221", "-87.64560"], "032 N LAKEWOOD AVE, Lakeview, Chicago, Illinois": ["42.00110", "-87.66350"], "016 W BARRY AVE, Lakeview, Chicago, Illinois": ["41.93773", "-87.63903"], "035 N PAULINA ST, Lakeview, Chicago, Illinois": ["41.88262", "-87.66911"], "056 S EVERETT DR, Hyde Park, Chicago, Illinois": ["41.92299", "-87.88681"], "031 N CLIFTON AVE, Lakeview, Chicago, Illinois": ["41.84772", "-87.68642"], "053 N LAKE SHORE DR NB, Edgewater, Chicago, Illinois": ["41.86740", "-87.61877"], "034 W SCHRAEDER DR, East Garfield Park, Chicago, Illinois": ["41.84820", "-87.62898"], "034 S DAN RYAN XPRS OB, Armour Square, Chicago, Illinois": ["41.88886", "-87.66545"], "006 W Barry Ave, Lakeview, Chicago, Illinois": ["41.93773", "-87.63903"], "030 N Sheridan Rd, Lakeview, Chicago, Illinois": ["41.99868", "-87.65725"], "043 N GREENVIEW AVE, Lakeview, Chicago, Illinois": ["41.92978", "-87.66561"], "029 N PAULINA ST, Lakeview, Chicago, Illinois": ["41.88235", "-87.66933"], "030 N BROADWAY, Lakeview, Chicago, Illinois": ["41.93296", "-87.64470"], "009 W Belmont Ave, Lakeview, Chicago, Illinois": ["41.93694", "-87.90050"], "009 W Dakin St, Lakeview, Chicago, Illinois": ["41.95364", "-87.65068"], "013 W FLETCHER ST, Lakeview, Chicago, Illinois": ["41.93903", "-87.64988"], "045 S LAKE SHORE DR SB, Kenwood, Chicago, Illinois": ["41.87888", "-87.61744"], "016 W WOLFRAM ST, Lakeview, Chicago, Illinois": ["41.93287", "-87.68450"], "033 N halsted st, Lakeview, Chicago, Illinois": ["41.88299", "-87.64709"], "013 W Belmont Ave, Lakeview, Chicago, Illinois": ["41.93694", "-87.90050"], "030 N Clifton Ave, Lakeview, Chicago, Illinois": ["41.91493", "-87.65885"], "035 N broadway, Lakeview, Chicago, Illinois": ["41.93296", "-87.64470"], "015 W Wellington Ave, Lakeview, Chicago, Illinois": ["41.93661", "-87.63737"], "012 W EDDY ST, Lakeview, Chicago, Illinois": ["41.94649", "-87.65595"], "035 N SEMINARY AVE, Lakeview, Chicago, Illinois": ["41.91659", "-87.65537"], "006 W Sheridan Rd, Lakeview, Chicago, Illinois": ["41.95295", "-87.64624"], "042 N GREENVIEW AVE, Lakeview, Chicago, Illinois": ["41.92978", "-87.66561"], "036 N BOSWORTH AVE, Lakeview, Chicago, Illinois": ["41.90689", "-87.66626"], "048 N MONTCLARE AVE, Norwood Park, Chicago, Illinois": ["41.92523", "-87.80396"], "014 W WELLINGTON AVE, Lakeview, Chicago, Illinois": ["41.93661", "-87.63737"], "017 W Wellington Ave, Lakeview, Chicago, Illinois": ["41.93661", "-87.63737"], "034 N LAKEWOOD AVE, Lakeview, Chicago, Illinois": ["42.00110", "-87.66350"], "012 N La Salle Dr, Near North Side, Chicago, Illinois": ["41.95353", "-87.67440"], "032 N CLIFTON AVE, Lakeview, Chicago, Illinois": ["41.91493", "-87.65885"], "031 N ORCHARD ST, Lakeview, Chicago, Illinois": ["41.93447", "-87.64670"], "017 W BELLE PLAINE AVE, Lakeview, Chicago, Illinois": ["41.95548", "-87.74669"], "017 W BERTEAU AVE, Lakeview, Chicago, Illinois": ["41.95800", "-87.66513"], "012 W WELLINGTON AVE, Lakeview, Chicago, Illinois": ["41.93661", "-87.63737"], "008 W Grace St, Lakeview, Chicago, Illinois": ["41.95221", "-87.64560"], "014 W OAKDALE AVE, Lakeview, Chicago, Illinois": ["41.93560", "-87.63831"], "011 N Frontier Ave, Near North Side, Chicago, Illinois": ["41.95353", "-87.67440"], "042 N HERMITAGE AVE, Lakeview, Chicago, Illinois": ["41.88273", "-87.67034"], "022 W DIVERSEY PKWY, Avondale, Chicago, Illinois": ["41.93332", "-87.63539"], "008 W Sheridan Rd, Lakeview, Chicago, Illinois": ["41.95295", "-87.64624"], "004 W Belmont Ave, Lakeview, Chicago, Illinois": ["41.93694", "-87.90050"], "016 W GRACE ST, Lakeview, Chicago, Illinois": ["41.95221", "-87.64560"], "031 N Sheffield Ave, Lakeview, Chicago, Illinois": ["41.90999", "-87.65309"], "037 N JANSSEN AVE, Lakeview, Chicago, Illinois": ["41.92299", "-87.66450"], "013 W Fletcher St, Lakeview, Chicago, Illinois": ["41.93903", "-87.64988"], "083 W ADDISON ST, O'Hare, Chicago, Illinois": ["41.94178", "-87.90162"], "038 N Janssen Ave, Lakeview, Chicago, Illinois": ["41.92299", "-87.66450"], "013 W George St, Lakeview, Chicago, Illinois": ["41.93453", "-87.64956"], "014 W Berteau Ave, Lakeview, Chicago, Illinois": ["41.95800", "-87.66513"], "028 N Clark St, Lakeview, Chicago, Illinois": ["41.88267", "-87.63096"], "037 N Janssen AVE, Lakeview, Chicago, Illinois": ["41.92299", "-87.66450"], "039 N SOUTHPORT AVE, Lakeview, Chicago, Illinois": ["41.94375", "-87.66344"], "004 W Barry Ave, Lakeview, Chicago, Illinois": ["41.93773", "-87.63903"], "005 W Roscoe ST, Lakeview, Chicago, Illinois": ["41.94296", "-87.64134"], "030 N LAKEWOOD AVE, Lakeview, Chicago, Illinois": ["42.00110", "-87.66350"], "041 N MC VICKER AVE, Portage Park, Chicago, Illinois": ["41.77221", "-87.77214"], "031 N Broadway, Lakeview, Chicago, Illinois": ["41.93296", "-87.64470"], "014 W HENDERSON ST, Lakeview, Chicago, Illinois": ["41.94256", "-87.65988"], "006 W OAKDALE AVE, Lakeview, Chicago, Illinois": ["41.93560", "-87.63831"], "034 N Southport Ave, Lakeview, Chicago, Illinois": ["41.94375", "-87.66344"], "009 W DIVERSEY PKWY, Lakeview, Chicago, Illinois": ["41.93353", "-87.63295"], "100 S BEVERLY AVE, Beverly, Chicago, Illinois": ["41.73341", "-87.67080"], "014 W ADDISON ST, Lakeview, Chicago, Illinois": ["41.94703", "-87.69870"], "008 N La Salle Dr, Near North Side, Chicago, Illinois": ["41.95353", "-87.67440"], "031 S LAKE SHORE DR NB, Douglas, Chicago, Illinois": ["41.85646", "-87.61634"], "036 N Wayne AVE, Lakeview, Chicago, Illinois": ["41.92436", "-87.66159"], "006 W SHERIDAN RD, Lakeview, Chicago, Illinois": ["41.95295", "-87.64624"]}